patato-0.6.1.dist-info/RECORD
patato-0.6.1.dist-info/METADATA
patato-0.6.1.dist-info/entry_points.txt
patato-0.6.1.dist-info/top_level.txt
patato-0.6.1.dist-info/WHEEL
patato-0.6.1.dist-info/licenses/LICENSE.MD
patato/_version.py
patato/__init__.py
patato/experimental/__init__.py
patato/experimental/simulation/__init__.py
patato/unmixing/unmixer.py
patato/unmixing/__init__.py
patato/unmixing/unmix_presets/haemoglobin_flow_phantom_all_wl.json
patato/unmixing/unmix_presets/haemoglobin_mitox.json
patato/unmixing/unmix_presets/haemoglobin_melanin.json
patato/unmixing/unmix_presets/haemoglobin.json
patato/unmixing/unmix_presets/hb_emma_water.json
patato/unmixing/unmix_presets/hb_icg.json
patato/unmixing/unmix_presets/haemoglobin_flow_phantom.json
patato/unmixing/spectra/__init__.py
patato/unmixing/spectra/spectra_files/ICG.csv
patato/unmixing/spectra/spectra_files/water_long.txt
patato/unmixing/spectra/spectra_files/water.txt
patato/unmixing/spectra/spectra_files/prahl.txt
patato/unmixing/spectra/spectra_files/Melanin.csv
patato/unmixing/spectra/spectra_files/lipids.txt
patato/core/__init__.py
patato/core/image_structures/image_structure_types.py
patato/core/image_structures/ultrasound_image.py
patato/core/image_structures/single_parameter_data.py
patato/core/image_structures/pa_time_data.py
patato/core/image_structures/reconstruction_image.py
patato/core/image_structures/single_image.py
patato/core/image_structures/image_sequence.py
patato/core/image_structures/unmixed_image.py
patato/core/image_structures/pa_raw_data.py
patato/core/image_structures/__init__.py
patato/recon/fourier_transform_rec.py
patato/recon/reconstruction_algorithm.py
patato/recon/backprojection_opencl.py
patato/recon/__init__.py
patato/recon/backprojection_reference.py
patato/recon/jax_model_based/__init__.py
patato/recon/recon_presets/backproject_standard_xz.json
patato/recon/recon_presets/backproject_standard_water_correction_new_ithera.json
patato/recon/recon_presets/backproject_standard_xy.json
patato/recon/recon_presets/backproject_clinical.json
patato/recon/recon_presets/backproject_clinical_xz.json
patato/recon/recon_presets/backproject_janek_sos.json
