Metadata-Version: 2.1
Name: patato
Version: 0.6.1
Summary: A Python Toolkit for the analysis of photoacoustic tomography data.
Author-email: Thomas Else <telse@ic.ac.uk>
License: MIT License
Project-URL: Homepage, https://github.com/bohndieklab/patato
Project-URL: Bug Tracker, https://github.com/bohndieklab/patato/issues
Project-URL: Documentation, https://patato.readthedocs.io
Keywords: photoacoustics,jax,tomography,reconstruction,spectral unmixing,dynamic contrast enhanced,backprojection,model based
Classifier: Intended Audience :: Education
Classifier: Intended Audience :: Science/Research
Classifier: Programming Language :: Python :: 3
Classifier: License :: OSI Approved :: MIT License
Classifier: Operating System :: OS Independent
Requires-Python: <3.14,>=3.8
License-File: LICENSE.MD
Requires-Dist: cython
Requires-Dist: shapely
Requires-Dist: pylops
Requires-Dist: h5py
Requires-Dist: pandas
Requires-Dist: xarray
Requires-Dist: numpy>=1.22
Requires-Dist: scipy
Requires-Dist: matplotlib
Requires-Dist: matplotlib-scalebar
Requires-Dist: dask
Requires-Dist: pybind11
Requires-Dist: jax[cpu]
Requires-Dist: customtkinter
Requires-Dist: tqdm
